<?xml version='1.0' encoding='UTF-8' standalone='yes' ?>
<hierarchy rotation="0">
  <node index="0" text="" resource-id="" class="android.widget.FrameLayout" package="com.zhiliaoapp.musically" content-desc="" checkable="false" checked="false" clickable="false" enabled="true" focusable="false" focused="false" scrollable="false" long-clickable="false" password="false" selected="false" visible-to-user="true" bounds="[0,346][720,1280]">
    <node index="0" text="" resource-id="" class="android.widget.FrameLayout" package="com.zhiliaoapp.musically" content-desc="" checkable="false" checked="false" clickable="false" enabled="true" focusable="false" focused="false" scrollable="false" long-clickable="false" password="false" selected="false" visible-to-user="true" bounds="[0,346][720,1280]">
      <node index="0" text="" resource-id="android:id/content" class="android.widget.FrameLayout" package="com.zhiliaoapp.musically" content-desc="" checkable="false" checked="false" clickable="false" enabled="true" focusable="false" focused="false" scrollable="false" long-clickable="false" password="false" selected="false" visible-to-user="true" bounds="[0,346][720,1280]">
        <node index="0" text="" resource-id="" class="android.widget.FrameLayout" package="com.zhiliaoapp.musically" content-desc="" checkable="false" checked="false" clickable="false" enabled="true" focusable="false" focused="false" scrollable="false" long-clickable="false" password="false" selected="false" visible-to-user="true" bounds="[0,346][720,1280]">
          <node index="0" text="" resource-id="" class="android.view.ViewGroup" package="com.zhiliaoapp.musically" content-desc="" checkable="false" checked="false" clickable="false" enabled="true" focusable="false" focused="false" scrollable="false" long-clickable="false" password="false" selected="false" visible-to-user="true" bounds="[0,346][720,1280]">
            <node index="0" text="" resource-id="com.zhiliaoapp.musically:id/o1p" class="android.widget.ScrollView" package="com.zhiliaoapp.musically" content-desc="" checkable="false" checked="false" clickable="false" enabled="true" focusable="true" focused="false" scrollable="true" long-clickable="false" password="false" selected="false" visible-to-user="true" bounds="[0,346][720,1280]">
              <node index="0" text="" resource-id="com.zhiliaoapp.musically:id/d0g" class="android.widget.LinearLayout" package="com.zhiliaoapp.musically" content-desc="" checkable="false" checked="false" clickable="false" enabled="true" focusable="false" focused="false" scrollable="false" long-clickable="false" password="false" selected="false" visible-to-user="true" bounds="[0,346][720,1280]">
                <node index="0" text="" resource-id="com.zhiliaoapp.musically:id/azg" class="android.widget.LinearLayout" package="com.zhiliaoapp.musically" content-desc="" checkable="false" checked="false" clickable="false" enabled="true" focusable="false" focused="false" scrollable="false" long-clickable="false" password="false" selected="false" visible-to-user="true" bounds="[16,362][704,842]">
                  <node index="0" text="" resource-id="com.zhiliaoapp.musically:id/rgq" class="android.view.ViewGroup" package="com.zhiliaoapp.musically" content-desc="" checkable="false" checked="false" clickable="true" enabled="true" focusable="true" focused="false" scrollable="false" long-clickable="true" password="false" selected="false" visible-to-user="true" bounds="[16,362][704,458]">
                    <node index="0" text="" resource-id="com.zhiliaoapp.musically:id/qzl" class="android.widget.ImageView" package="com.zhiliaoapp.musically" content-desc="" checkable="false" checked="false" clickable="false" enabled="true" focusable="false" focused="false" scrollable="false" long-clickable="false" password="false" selected="false" visible-to-user="true" bounds="[48,386][96,434]" />
                    <node index="1" text="Flip camera" resource-id="com.zhiliaoapp.musically:id/r08" class="android.widget.TextView" package="com.zhiliaoapp.musically" content-desc="" checkable="false" checked="false" clickable="false" enabled="true" focusable="false" focused="false" scrollable="false" long-clickable="false" password="false" selected="false" visible-to-user="true" bounds="[112,391][275,429]" />
                  </node>
                  <node index="1" text="" resource-id="com.zhiliaoapp.musically:id/rgq" class="android.view.ViewGroup" package="com.zhiliaoapp.musically" content-desc="" checkable="false" checked="false" clickable="true" enabled="true" focusable="true" focused="false" scrollable="false" long-clickable="true" password="false" selected="false" visible-to-user="true" bounds="[16,458][704,554]">
                    <node index="0" text="" resource-id="com.zhiliaoapp.musically:id/qzl" class="android.widget.ImageView" package="com.zhiliaoapp.musically" content-desc="" checkable="false" checked="false" clickable="false" enabled="true" focusable="false" focused="false" scrollable="false" long-clickable="false" password="false" selected="false" visible-to-user="true" bounds="[48,482][96,530]" />
                    <node index="1" text="Mirror your video" resource-id="com.zhiliaoapp.musically:id/r08" class="android.widget.TextView" package="com.zhiliaoapp.musically" content-desc="" checkable="false" checked="false" clickable="false" enabled="true" focusable="false" focused="false" scrollable="false" long-clickable="false" password="false" selected="false" visible-to-user="true" bounds="[112,487][354,525]" />
                    <node index="2" text="" resource-id="com.zhiliaoapp.musically:id/jzo" class="android.widget.Switch" package="com.zhiliaoapp.musically" content-desc="" checkable="true" checked="true" clickable="true" enabled="false" focusable="true" focused="false" scrollable="false" long-clickable="false" password="false" selected="false" visible-to-user="true" bounds="[576,482][672,530]" />
                  </node>
                  <node index="2" text="" resource-id="com.zhiliaoapp.musically:id/rgq" class="android.view.ViewGroup" package="com.zhiliaoapp.musically" content-desc="" checkable="false" checked="false" clickable="true" enabled="true" focusable="true" focused="false" scrollable="false" long-clickable="true" password="false" selected="false" visible-to-user="true" bounds="[16,554][704,650]">
                    <node index="0" text="" resource-id="com.zhiliaoapp.musically:id/qzl" class="android.widget.ImageView" package="com.zhiliaoapp.musically" content-desc="" checkable="false" checked="false" clickable="false" enabled="true" focusable="false" focused="false" scrollable="false" long-clickable="false" password="false" selected="false" visible-to-user="true" bounds="[48,578][96,626]" />
                    <node index="1" text="Mute microphone" resource-id="com.zhiliaoapp.musically:id/r08" class="android.widget.TextView" package="com.zhiliaoapp.musically" content-desc="" checkable="false" checked="false" clickable="false" enabled="true" focusable="false" focused="false" scrollable="false" long-clickable="false" password="false" selected="false" visible-to-user="true" bounds="[112,583][361,621]" />
                    <node index="2" text="" resource-id="com.zhiliaoapp.musically:id/kbo" class="android.widget.Switch" package="com.zhiliaoapp.musically" content-desc="" checkable="true" checked="false" clickable="true" enabled="false" focusable="true" focused="false" scrollable="false" long-clickable="false" password="false" selected="false" visible-to-user="true" bounds="[576,578][672,626]" />
                  </node>
                  <node index="3" text="" resource-id="com.zhiliaoapp.musically:id/rgq" class="android.view.ViewGroup" package="com.zhiliaoapp.musically" content-desc="" checkable="false" checked="false" clickable="true" enabled="true" focusable="true" focused="false" scrollable="false" long-clickable="true" password="false" selected="false" visible-to-user="true" bounds="[16,650][704,746]">
                    <node index="0" text="" resource-id="com.zhiliaoapp.musically:id/qzl" class="android.widget.ImageView" package="com.zhiliaoapp.musically" content-desc="" checkable="false" checked="false" clickable="false" enabled="true" focusable="false" focused="false" scrollable="false" long-clickable="false" password="false" selected="false" visible-to-user="true" bounds="[48,674][96,722]" />
                    <node index="1" text="Pause LIVE" resource-id="com.zhiliaoapp.musically:id/r08" class="android.widget.TextView" package="com.zhiliaoapp.musically" content-desc="" checkable="false" checked="false" clickable="false" enabled="true" focusable="false" focused="false" scrollable="false" long-clickable="false" password="false" selected="false" visible-to-user="true" bounds="[112,679][266,717]" />
                  </node>
                  <node index="4" text="" resource-id="com.zhiliaoapp.musically:id/rgq" class="android.view.ViewGroup" package="com.zhiliaoapp.musically" content-desc="" checkable="false" checked="false" clickable="true" enabled="true" focusable="true" focused="false" scrollable="false" long-clickable="true" password="false" selected="false" visible-to-user="true" bounds="[16,746][704,842]">
                    <node index="0" text="" resource-id="com.zhiliaoapp.musically:id/qzl" class="android.widget.ImageView" package="com.zhiliaoapp.musically" content-desc="" checkable="false" checked="false" clickable="false" enabled="true" focusable="false" focused="false" scrollable="false" long-clickable="false" password="false" selected="false" visible-to-user="true" bounds="[48,770][96,818]" />
                    <node index="1" text="Settings" resource-id="com.zhiliaoapp.musically:id/r08" class="android.widget.TextView" package="com.zhiliaoapp.musically" content-desc="" checkable="false" checked="false" clickable="false" enabled="true" focusable="false" focused="false" scrollable="false" long-clickable="false" password="false" selected="false" visible-to-user="true" bounds="[112,775][229,813]" />
                    <node index="2" text="" resource-id="com.zhiliaoapp.musically:id/nlt" class="android.widget.ImageView" package="com.zhiliaoapp.musically" content-desc="" checkable="false" checked="false" clickable="false" enabled="true" focusable="false" focused="false" scrollable="false" long-clickable="false" password="false" selected="false" visible-to-user="true" bounds="[640,778][672,810]" />
                  </node>
                </node>
                <node index="1" text="" resource-id="com.zhiliaoapp.musically:id/om8" class="android.widget.LinearLayout" package="com.zhiliaoapp.musically" content-desc="" checkable="false" checked="false" clickable="false" enabled="true" focusable="false" focused="false" scrollable="false" long-clickable="false" password="false" selected="false" visible-to-user="true" bounds="[16,858][704,1280]">
                  <node index="0" text="" resource-id="com.zhiliaoapp.musically:id/rgq" class="android.view.ViewGroup" package="com.zhiliaoapp.musically" content-desc="" checkable="false" checked="false" clickable="true" enabled="true" focusable="true" focused="false" scrollable="false" long-clickable="true" password="false" selected="false" visible-to-user="true" bounds="[16,858][704,954]">
                    <node index="0" text="" resource-id="com.zhiliaoapp.musically:id/qzl" class="android.widget.ImageView" package="com.zhiliaoapp.musically" content-desc="" checkable="false" checked="false" clickable="false" enabled="true" focusable="false" focused="false" scrollable="false" long-clickable="false" password="false" selected="false" visible-to-user="true" bounds="[48,882][96,930]" />
                    <node index="1" text="LIVE Gifts" resource-id="com.zhiliaoapp.musically:id/r08" class="android.widget.TextView" package="com.zhiliaoapp.musically" content-desc="" checkable="false" checked="false" clickable="false" enabled="true" focusable="false" focused="false" scrollable="false" long-clickable="false" password="false" selected="false" visible-to-user="true" bounds="[112,887][249,925]" />
                    <node index="2" text="" resource-id="com.zhiliaoapp.musically:id/r06" class="android.view.View" package="com.zhiliaoapp.musically" content-desc="" checkable="false" checked="false" clickable="false" enabled="true" focusable="false" focused="false" scrollable="false" long-clickable="false" password="false" selected="false" visible-to-user="true" bounds="[624,898][640,914]" />
                    <node index="3" text="" resource-id="com.zhiliaoapp.musically:id/nlt" class="android.widget.ImageView" package="com.zhiliaoapp.musically" content-desc="" checkable="false" checked="false" clickable="false" enabled="true" focusable="false" focused="false" scrollable="false" long-clickable="false" password="false" selected="false" visible-to-user="true" bounds="[640,890][672,922]" />
                  </node>
                  <node index="1" text="" resource-id="com.zhiliaoapp.musically:id/rgq" class="android.view.ViewGroup" package="com.zhiliaoapp.musically" content-desc="" checkable="false" checked="false" clickable="true" enabled="true" focusable="true" focused="false" scrollable="false" long-clickable="true" password="false" selected="false" visible-to-user="true" bounds="[16,954][704,1050]">
                    <node index="0" text="" resource-id="com.zhiliaoapp.musically:id/qzl" class="android.widget.ImageView" package="com.zhiliaoapp.musically" content-desc="" checkable="false" checked="false" clickable="false" enabled="true" focusable="false" focused="false" scrollable="false" long-clickable="false" password="false" selected="false" visible-to-user="true" bounds="[48,978][96,1026]" />
                    <node index="1" text="Comment" resource-id="com.zhiliaoapp.musically:id/r08" class="android.widget.TextView" package="com.zhiliaoapp.musically" content-desc="" checkable="false" checked="false" clickable="false" enabled="true" focusable="false" focused="false" scrollable="false" long-clickable="false" password="false" selected="false" visible-to-user="true" bounds="[112,983][249,1021]" />
                  </node>
                  <node index="2" text="" resource-id="com.zhiliaoapp.musically:id/rgq" class="android.view.ViewGroup" package="com.zhiliaoapp.musically" content-desc="" checkable="false" checked="false" clickable="true" enabled="true" focusable="true" focused="false" scrollable="false" long-clickable="true" password="false" selected="false" visible-to-user="true" bounds="[16,1050][704,1146]">
                    <node index="0" text="" resource-id="com.zhiliaoapp.musically:id/qzl" class="android.widget.ImageView" package="com.zhiliaoapp.musically" content-desc="" checkable="false" checked="false" clickable="false" enabled="true" focusable="false" focused="false" scrollable="false" long-clickable="false" password="false" selected="false" visible-to-user="true" bounds="[48,1074][96,1122]" />
                    <node index="1" text="About me" resource-id="com.zhiliaoapp.musically:id/r08" class="android.widget.TextView" package="com.zhiliaoapp.musically" content-desc="" checkable="false" checked="false" clickable="false" enabled="true" focusable="false" focused="false" scrollable="false" long-clickable="false" password="false" selected="false" visible-to-user="true" bounds="[112,1079][249,1117]" />
                    <node index="2" text="" resource-id="com.zhiliaoapp.musically:id/nlt" class="android.widget.ImageView" package="com.zhiliaoapp.musically" content-desc="" checkable="false" checked="false" clickable="false" enabled="true" focusable="false" focused="false" scrollable="false" long-clickable="false" password="false" selected="false" visible-to-user="true" bounds="[640,1082][672,1114]" />
                  </node>
                  <node index="3" text="" resource-id="com.zhiliaoapp.musically:id/rgq" class="android.view.ViewGroup" package="com.zhiliaoapp.musically" content-desc="" checkable="false" checked="false" clickable="true" enabled="true" focusable="true" focused="false" scrollable="false" long-clickable="true" password="false" selected="false" visible-to-user="true" bounds="[16,1146][704,1242]">
                    <node index="0" text="" resource-id="com.zhiliaoapp.musically:id/qzl" class="android.widget.ImageView" package="com.zhiliaoapp.musically" content-desc="" checkable="false" checked="false" clickable="false" enabled="true" focusable="false" focused="false" scrollable="false" long-clickable="false" password="false" selected="false" visible-to-user="true" bounds="[48,1170][96,1218]" />
                    <node index="1" text="LIVE Events" resource-id="com.zhiliaoapp.musically:id/r08" class="android.widget.TextView" package="com.zhiliaoapp.musically" content-desc="" checkable="false" checked="false" clickable="false" enabled="true" focusable="false" focused="false" scrollable="false" long-clickable="false" password="false" selected="false" visible-to-user="true" bounds="[112,1175][274,1213]" />
                    <node index="2" text="" resource-id="com.zhiliaoapp.musically:id/nlt" class="android.widget.ImageView" package="com.zhiliaoapp.musically" content-desc="" checkable="false" checked="false" clickable="false" enabled="true" focusable="false" focused="false" scrollable="false" long-clickable="false" password="false" selected="false" visible-to-user="true" bounds="[640,1178][672,1210]" />
                  </node>
                  <node index="4" text="" resource-id="com.zhiliaoapp.musically:id/rgq" class="android.view.ViewGroup" package="com.zhiliaoapp.musically" content-desc="" checkable="false" checked="false" clickable="true" enabled="true" focusable="true" focused="false" scrollable="false" long-clickable="true" password="false" selected="false" visible-to-user="true" bounds="[16,1242][704,1280]">
                    <node index="0" text="" resource-id="com.zhiliaoapp.musically:id/qzl" class="android.widget.ImageView" package="com.zhiliaoapp.musically" content-desc="" checkable="false" checked="false" clickable="false" enabled="true" focusable="false" focused="false" scrollable="false" long-clickable="false" password="false" selected="false" visible-to-user="true" bounds="[48,1266][96,1280]" />
                    <node index="1" text="Activities" resource-id="com.zhiliaoapp.musically:id/r08" class="android.widget.TextView" package="com.zhiliaoapp.musically" content-desc="" checkable="false" checked="false" clickable="false" enabled="true" focusable="false" focused="false" scrollable="false" long-clickable="false" password="false" selected="false" visible-to-user="true" bounds="[112,1271][243,1280]" />
                    <node index="2" text="" resource-id="com.zhiliaoapp.musically:id/nlt" class="android.widget.ImageView" package="com.zhiliaoapp.musically" content-desc="" checkable="false" checked="false" clickable="false" enabled="true" focusable="false" focused="false" scrollable="false" long-clickable="false" password="false" selected="false" visible-to-user="true" bounds="[640,1274][672,1280]" />
                  </node>
                </node>
              </node>
            </node>
          </node>
        </node>
      </node>
    </node>
  </node>
  <node index="0" text="" resource-id="" class="android.widget.FrameLayout" package="com.android.systemui" content-desc="" checkable="false" checked="false" clickable="false" enabled="true" focusable="false" focused="false" scrollable="false" long-clickable="false" password="false" selected="false" visible-to-user="true" bounds="[0,0][720,48]">
    <node index="0" text="" resource-id="com.android.systemui:id/status_bar_launch_animation_container" class="android.widget.FrameLayout" package="com.android.systemui" content-desc="" checkable="false" checked="false" clickable="false" enabled="true" focusable="false" focused="false" scrollable="false" long-clickable="false" password="false" selected="false" visible-to-user="true" bounds="[0,0][720,48]" />
    <node index="1" text="" resource-id="com.android.systemui:id/status_bar_container" class="android.widget.FrameLayout" package="com.android.systemui" content-desc="" checkable="false" checked="false" clickable="false" enabled="true" focusable="false" focused="false" scrollable="false" long-clickable="false" password="false" selected="false" visible-to-user="true" bounds="[0,0][720,48]">
      <node index="0" text="" resource-id="com.android.systemui:id/status_bar" class="android.widget.FrameLayout" package="com.android.systemui" content-desc="" checkable="false" checked="false" clickable="false" enabled="true" focusable="false" focused="false" scrollable="false" long-clickable="false" password="false" selected="false" visible-to-user="true" bounds="[0,0][720,48]">
        <node index="0" text="" resource-id="com.android.systemui:id/status_bar_contents" class="android.widget.LinearLayout" package="com.android.systemui" content-desc="" checkable="false" checked="false" clickable="false" enabled="true" focusable="false" focused="false" scrollable="false" long-clickable="false" password="false" selected="false" visible-to-user="true" bounds="[0,0][680,48]">
          <node index="0" text="" resource-id="" class="android.widget.FrameLayout" package="com.android.systemui" content-desc="" checkable="false" checked="false" clickable="false" enabled="true" focusable="false" focused="false" scrollable="false" long-clickable="false" password="false" selected="false" visible-to-user="true" bounds="[16,0][340,48]">
            <node index="0" text="" resource-id="com.android.systemui:id/status_bar_left_side" class="android.widget.LinearLayout" package="com.android.systemui" content-desc="" checkable="false" checked="false" clickable="false" enabled="true" focusable="false" focused="false" scrollable="false" long-clickable="false" password="false" selected="false" visible-to-user="true" bounds="[16,0][340,48]">
              <node index="0" text="17:58" resource-id="com.android.systemui:id/clock" class="android.widget.TextView" package="com.android.systemui" content-desc="17:58" checkable="false" checked="false" clickable="false" enabled="true" focusable="false" focused="false" scrollable="false" long-clickable="false" password="false" selected="false" visible-to-user="true" bounds="[16,0][91,48]" />
              <node index="1" text="" resource-id="com.android.systemui:id/notification_icon_area" class="android.widget.FrameLayout" package="com.android.systemui" content-desc="" checkable="false" checked="false" clickable="false" enabled="true" focusable="false" focused="false" scrollable="false" long-clickable="false" password="false" selected="false" visible-to-user="true" bounds="[91,0][340,48]">
                <node index="0" text="" resource-id="com.android.systemui:id/notification_icon_area_inner" class="android.widget.LinearLayout" package="com.android.systemui" content-desc="" checkable="false" checked="false" clickable="false" enabled="true" focusable="false" focused="false" scrollable="false" long-clickable="false" password="false" selected="false" visible-to-user="true" bounds="[91,0][340,48]">
                  <node index="0" text="" resource-id="com.android.systemui:id/notificationIcons" class="android.widget.FrameLayout" package="com.android.systemui" content-desc="" checkable="false" checked="false" clickable="false" enabled="true" focusable="false" focused="false" scrollable="false" long-clickable="false" password="false" selected="false" visible-to-user="true" bounds="[91,0][340,48]">
                    <node index="0" text="" resource-id="" class="android.widget.ImageView" package="com.android.systemui" content-desc="Android System notification: Data warning" checkable="false" checked="false" clickable="false" enabled="true" focusable="false" focused="false" scrollable="false" long-clickable="false" password="false" selected="false" visible-to-user="true" bounds="[91,0][135,48]" />
                    <node index="1" text="" resource-id="" class="android.widget.ImageView" package="com.android.systemui" content-desc="TikTok notification: " checkable="false" checked="false" clickable="false" enabled="true" focusable="false" focused="false" scrollable="false" long-clickable="false" password="false" selected="false" visible-to-user="true" bounds="[135,0][179,48]" />
                    <node index="2" text="" resource-id="" class="android.widget.ImageView" package="com.android.systemui" content-desc="TikTok notification: Gehe LIVE, hole dir deine Diamanten &#128640;" checkable="false" checked="false" clickable="false" enabled="true" focusable="false" focused="false" scrollable="false" long-clickable="false" password="false" selected="false" visible-to-user="true" bounds="[179,0][223,48]" />
                    <node index="3" text="" resource-id="" class="android.widget.ImageView" package="com.android.systemui" content-desc="Android System notification: Check access settings" checkable="false" checked="false" clickable="false" enabled="true" focusable="false" focused="false" scrollable="false" long-clickable="false" password="false" selected="false" visible-to-user="true" bounds="[223,0][267,48]" />
                    <node index="4" text="" resource-id="" class="android.widget.ImageView" package="com.android.systemui" content-desc="Security and privacy notification: Protect your data from phone theft" checkable="false" checked="false" clickable="false" enabled="true" focusable="false" focused="false" scrollable="false" long-clickable="false" password="false" selected="false" visible-to-user="true" bounds="[267,0][311,48]" />
                  </node>
                </node>
              </node>
            </node>
          </node>
          <node index="1" text="" resource-id="com.android.systemui:id/system_icon_area" class="android.widget.LinearLayout" package="com.android.systemui" content-desc="" checkable="false" checked="false" clickable="false" enabled="true" focusable="false" focused="false" scrollable="false" long-clickable="false" password="false" selected="false" visible-to-user="true" bounds="[340,0][664,48]">
            <node index="0" text="" resource-id="com.android.systemui:id/system_icons" class="android.widget.LinearLayout" package="com.android.systemui" content-desc="" checkable="false" checked="false" clickable="false" enabled="true" focusable="false" focused="false" scrollable="false" long-clickable="false" password="false" selected="false" visible-to-user="true" bounds="[340,0][664,48]">
              <node index="0" text="" resource-id="com.android.systemui:id/statusIcons" class="android.widget.LinearLayout" package="com.android.systemui" content-desc="" checkable="false" checked="false" clickable="false" enabled="true" focusable="false" focused="false" scrollable="false" long-clickable="false" password="false" selected="false" visible-to-user="true" bounds="[340,0][648,48]">
                <node index="0" text="" resource-id="com.android.systemui:id/mobile_combo" class="android.widget.FrameLayout" package="com.android.systemui" content-desc="Phone signal full." checkable="false" checked="false" clickable="false" enabled="true" focusable="false" focused="false" scrollable="false" long-clickable="false" password="false" selected="false" visible-to-user="true" bounds="[542,2][636,46]">
                  <node index="0" text="" resource-id="com.android.systemui:id/mobile_group" class="android.widget.LinearLayout" package="com.android.systemui" content-desc="" checkable="false" checked="false" clickable="false" enabled="true" focusable="false" focused="false" scrollable="false" long-clickable="false" password="false" selected="false" visible-to-user="true" bounds="[542,2][636,46]">
                    <node index="0" text="" resource-id="com.android.systemui:id/inout_container" class="android.widget.FrameLayout" package="com.android.systemui" content-desc="" checkable="false" checked="false" clickable="false" enabled="true" focusable="false" focused="false" scrollable="false" long-clickable="false" password="false" selected="false" visible-to-user="true" bounds="[542,7][555,41]">
                      <node index="0" text="" resource-id="com.android.systemui:id/mobile_in" class="android.widget.ImageView" package="com.android.systemui" content-desc="" checkable="false" checked="false" clickable="false" enabled="true" focusable="false" focused="false" scrollable="false" long-clickable="false" password="false" selected="false" visible-to-user="true" bounds="[542,7][555,37]" />
                      <node index="1" text="" resource-id="com.android.systemui:id/mobile_out" class="android.widget.ImageView" package="com.android.systemui" content-desc="" checkable="false" checked="false" clickable="false" enabled="true" focusable="false" focused="false" scrollable="false" long-clickable="false" password="false" selected="false" visible-to-user="true" bounds="[542,7][555,37]" />
                    </node>
                    <node index="1" text="" resource-id="com.android.systemui:id/mobile_type" class="android.widget.ImageView" package="com.android.systemui" content-desc="4G" checkable="false" checked="false" clickable="false" enabled="true" focusable="false" focused="false" scrollable="false" long-clickable="false" password="false" selected="false" visible-to-user="true" bounds="[555,8][606,40]" />
                    <node index="2" text="" resource-id="" class="android.widget.FrameLayout" package="com.android.systemui" content-desc="" checkable="false" checked="false" clickable="false" enabled="true" focusable="false" focused="false" scrollable="false" long-clickable="false" password="false" selected="false" visible-to-user="true" bounds="[606,9][636,39]">
                      <node index="0" text="" resource-id="com.android.systemui:id/mobile_signal" class="android.widget.ImageView" package="com.android.systemui" content-desc="" checkable="false" checked="false" clickable="false" enabled="true" focusable="false" focused="false" scrollable="false" long-clickable="false" password="false" selected="false" visible-to-user="true" bounds="[606,9][636,39]" />
                    </node>
                  </node>
                </node>
              </node>
              <node index="1" text="" resource-id="com.android.systemui:id/battery" class="android.widget.LinearLayout" package="com.android.systemui" content-desc="Battery 50 per cent." checkable="false" checked="false" clickable="false" enabled="true" focusable="false" focused="false" scrollable="false" long-clickable="false" password="false" selected="false" visible-to-user="true" bounds="[648,0][664,48]">
                <node index="0" text="" resource-id="" class="android.widget.ImageView" package="com.android.systemui" content-desc="" checkable="false" checked="false" clickable="false" enabled="true" focusable="false" focused="false" scrollable="false" long-clickable="false" password="false" selected="false" visible-to-user="true" bounds="[648,11][664,37]" />
              </node>
            </node>
          </node>
        </node>
      </node>
    </node>
    <node index="2" text="" resource-id="com.android.systemui:id/container" class="android.widget.FrameLayout" package="com.android.systemui" content-desc="" checkable="false" checked="false" clickable="false" enabled="true" focusable="false" focused="false" scrollable="false" long-clickable="false" password="false" selected="false" visible-to-user="true" bounds="[0,0][720,48]" />
  </node>
  <node index="0" text="" resource-id="com.huang.autorunmarket:id/image" class="android.widget.ImageView" package="com.huang.autorunmarket" content-desc="" checkable="false" checked="false" clickable="false" enabled="true" focusable="false" focused="false" scrollable="false" long-clickable="false" password="false" selected="false" visible-to-user="true" bounds="[636,514][720,598]" />
</hierarchy>